py_pglite/__init__.py
py_pglite/clients.py
py_pglite/config.py
py_pglite/django/__init__.py
py_pglite/django/backend/__init__.py
py_pglite/django/backend/base.py
py_pglite/django/fixtures.py
py_pglite/django/utils.py
py_pglite/extensions.py
py_pglite/fixtures.py
py_pglite/manager.py
py_pglite/pytest_plugin.py
py_pglite/sqlalchemy/__init__.py
py_pglite/sqlalchemy/fixtures.py
py_pglite/sqlalchemy/manager.py
py_pglite/sqlalchemy/manager_async.py
py_pglite/sqlalchemy/utils.py
py_pglite/utils.py
py_pglite-0.5.3.dist-info/WHEEL
py_pglite-0.5.3.dist-info/entry_points.txt
py_pglite-0.5.3.dist-info/METADATA
py_pglite-0.5.3.dist-info/RECORD
