Metadata-Version: 2.4
Name: py-pglite
Version: 0.5.3
Summary: Python testing library for PGlite - in-memory PostgreSQL for tests
Keywords: testing,postgresql,pglite,database,pytest,sqlalchemy,sqlmodel,django,pytest-django
Author: Wey Gu
Author-email: Wey Gu <weyl.gu@gmail.com>
License-Expression: Apache-2.0
Classifier: Development Status :: 4 - Beta
Classifier: Intended Audience :: Developers
Classifier: License :: OSI Approved :: Apache Software License
Classifier: Programming Language :: Python :: 3
Classifier: Programming Language :: Python :: 3.10
Classifier: Programming Language :: Python :: 3.11
Classifier: Programming Language :: Python :: 3.12
Classifier: Programming Language :: Python :: 3.13
Classifier: Programming Language :: Python :: 3.14
Classifier: Topic :: Database
Classifier: Topic :: Software Development :: Testing
Classifier: Topic :: Software Development :: Libraries :: Python Modules
Requires-Dist: psutil>=6.0.0
Requires-Dist: py-pglite[psycopg] ; extra == 'all'
Requires-Dist: py-pglite[asyncpg] ; extra == 'all'
Requires-Dist: py-pglite[sqlalchemy] ; extra == 'all'
Requires-Dist: py-pglite[sqlmodel] ; extra == 'all'
Requires-Dist: py-pglite[django] ; extra == 'all'
Requires-Dist: py-pglite[fastapi] ; extra == 'all'
Requires-Dist: py-pglite[extensions] ; extra == 'all'
Requires-Dist: py-pglite[examples] ; extra == 'all'
Requires-Dist: pytest-asyncio>=0.21.0 ; extra == 'all'
Requires-Dist: asyncpg>=0.29.0 ; extra == 'async'
Requires-Dist: pytest-asyncio>=0.21.0 ; extra == 'async'
Requires-Dist: asyncpg>=0.29.0 ; extra == 'asyncpg'
Requires-Dist: django>=4.0.0 ; extra == 'django'
Requires-Dist: pytest-django>=4.5.0 ; extra == 'django'
Requires-Dist: py-pglite[fastapi] ; extra == 'examples'
Requires-Dist: python-jose>=3.3.0 ; extra == 'examples'
Requires-Dist: passlib>=1.7.4 ; extra == 'examples'
Requires-Dist: bcrypt>=4.3.0 ; extra == 'examples'
Requires-Dist: pgvector>=0.4.1 ; extra == 'extensions'
Requires-Dist: numpy>=1.0.0 ; extra == 'extensions'
Requires-Dist: sqlalchemy>=2.0.41 ; extra == 'fastapi'
Requires-Dist: fastapi>=0.115.12 ; extra == 'fastapi'
Requires-Dist: sqlmodel>=0.0.24 ; extra == 'fastapi'
Requires-Dist: httpx>=0.27.0 ; extra == 'fastapi'
Requires-Dist: psycopg>=3.0.0 ; extra == 'psycopg'
Requires-Dist: sqlalchemy>=2.0.41 ; extra == 'sqlalchemy'
Requires-Dist: sqlalchemy>=2.0.41 ; extra == 'sqlmodel'
Requires-Dist: sqlmodel>=0.0.24 ; extra == 'sqlmodel'
Requires-Dist: py-pglite[extensions] ; extra == 'test-extensions'
Requires-Python: >=3.10
Project-URL: Documentation, https://github.com/wey-gu/py-pglite#readme
Project-URL: Homepage, https://github.com/wey-gu/py-pglite
Project-URL: Issues, https://github.com/wey-gu/py-pglite/issues
Project-URL: Repository, https://github.com/wey-gu/py-pglite
Provides-Extra: all
Provides-Extra: async
Provides-Extra: asyncpg
Provides-Extra: django
Provides-Extra: examples
Provides-Extra: extensions
Provides-Extra: fastapi
Provides-Extra: psycopg
Provides-Extra: sqlalchemy
Provides-Extra: sqlmodel
Provides-Extra: test-extensions
